README.md
setup.py
JSETracker.egg-info/PKG-INFO
JSETracker.egg-info/SOURCES.txt
JSETracker.egg-info/dependency_links.txt
JSETracker.egg-info/requires.txt
JSETracker.egg-info/top_level.txt
jsetracker/JSE.py
jsetracker/__init__.py