Metadata-Version: 2.1
Name: JSETracker
Version: 1.0.0
Summary: Real Time JSE stock data for free
Home-page: https://github.com/SNR99/JSETracker
Author: Ntwanano Rikhotso
Author-email: sanele.rikhotso.99@gmail.com
License: MIT
Keywords: Python,JSE,Stock Price API,Stock Price,JSE API ,Johannesburg Stock Exchange,API,Johannesburg Stock Exchange API
Platform: UNKNOWN
Classifier: Development Status :: 5 - Production/Stable
Classifier: Intended Audience :: Developers
Classifier: Programming Language :: Python :: 3
Classifier: Operating System :: OS Independent
Classifier: 
